{
  "package": {
    "name": "mysqld-exporter",
    "repo": "debian",
    "subject": "phakudiapptuittestorg"
  },

  "version": {
    "name": "@PACKAGE_VERSION@",
    "desc": "Version @PACKAGE_VERSION@",
    "released": "@PACKAGE_DATE@",
    "vcs_tag": "mysqld_exporter-v@PACKAGE_VERSION@"
  },

  "files":
  [
    {
      "includePattern": "mysqld_exporter/deb/dist/(.*\\.deb)", "uploadPattern": "/pool/m/mysqld-exporter/$1",
      "matrixParams": {
        "deb_distribution": "stable,jessie,stretch,artful,wheezy,xenial,zesty,trusty",
        "deb_component": "mysqld-exporter",
        "deb_architecture": "i386,amd64",
        "override": 1
      }
    }
  ],
  "publish": true
}